marimo/AGENTS.md
marimo/__init__.py
marimo/__main__.py
marimo/_ai/__init__.py
marimo/_ai/_convert.py
marimo/_ai/_pydantic_ai_utils.py
marimo/_ai/_tools/base.py
marimo/_ai/_tools/tools/cells.py
marimo/_ai/_tools/tools/datasource.py
marimo/_ai/_tools/tools/errors.py
marimo/_ai/_tools/tools/lint.py
marimo/_ai/_tools/tools/notebooks.py
marimo/_ai/_tools/tools/rules.py
marimo/_ai/_tools/tools/tables_and_variables.py
marimo/_ai/_tools/tools_registry.py
marimo/_ai/_tools/types.py
marimo/_ai/_tools/utils/exceptions.py
marimo/_ai/_tools/utils/output_cleaning.py
marimo/_ai/_types.py
marimo/_ai/llm/__init__.py
marimo/_ai/llm/_impl.py
marimo/_ai/text_to_notebook.py
marimo/_ast/__init__.py
marimo/_ast/app.py
marimo/_ast/app_config.py
marimo/_ast/cell.py
marimo/_ast/cell_id.py
marimo/_ast/cell_manager.py
marimo/_ast/codegen.py
marimo/_ast/compiler.py
marimo/_ast/errors.py
marimo/_ast/fast_stack.py
marimo/_ast/load.py
marimo/_ast/models.py
marimo/_ast/names.py
marimo/_ast/parse.py
marimo/_ast/pytest.py
marimo/_ast/sql_utils.py
marimo/_ast/sql_visitor.py
marimo/_ast/toplevel.py
marimo/_ast/transformers.py
marimo/_ast/variables.py
marimo/_ast/visitor.py
marimo/_cli/__init__.py
marimo/_cli/cli.py
marimo/_cli/cli_validators.py
marimo/_cli/config/commands.py
marimo/_cli/config/utils.py
marimo/_cli/convert/commands.py
marimo/_cli/convert/utils.py
marimo/_cli/development/commands.py
marimo/_cli/envinfo.py
marimo/_cli/export/cloudflare.py
marimo/_cli/export/commands.py
marimo/_cli/file_path.py
marimo/_cli/parse_args.py
marimo/_cli/print.py
marimo/_cli/run_docker.py
marimo/_cli/sandbox.py
marimo/_cli/upgrade.py
marimo/_cli/utils.py
marimo/_config/__init__.py
marimo/_config/cli_state.py
marimo/_config/config.py
marimo/_config/manager.py
marimo/_config/packages.py
marimo/_config/reader.py
marimo/_config/secrets.py
marimo/_config/settings.py
marimo/_config/utils.py
marimo/_convert/__init__.py
marimo/_convert/common/__init__.py
marimo/_convert/common/comment_preserver.py
marimo-0.19.7.dist-info/WHEEL
marimo-0.19.7.dist-info/entry_points.txt
marimo-0.19.7.dist-info/METADATA
marimo-0.19.7.dist-info/RECORD
