Metadata-Version: 2.3
Name: marimo
Version: 0.19.7
Summary: A library for making reactive notebooks and apps
License: 
Classifier: Operating System :: OS Independent
Classifier: License :: OSI Approved :: Apache Software License
Classifier: Environment :: Console
Classifier: Environment :: Web Environment
Classifier: Intended Audience :: Developers
Classifier: Intended Audience :: Science/Research
Classifier: Intended Audience :: Education
Classifier: Programming Language :: Python
Classifier: Programming Language :: Python :: 3.10
Classifier: Programming Language :: Python :: 3.11
Classifier: Programming Language :: Python :: 3.12
Classifier: Programming Language :: Python :: 3.13
Classifier: Programming Language :: Python :: 3.14
Classifier: Programming Language :: Python :: 3 :: Only
Requires-Dist: click>=8.0,<9
Requires-Dist: jedi>=0.18.0
Requires-Dist: markdown>=3.6,<4
Requires-Dist: pymdown-extensions>=10.15,<11
Requires-Dist: pygments>=2.19,<3
Requires-Dist: tomlkit>=0.12.0
Requires-Dist: pyyaml>=6.0.1
Requires-Dist: uvicorn>=0.22.0
Requires-Dist: starlette>=0.37.2
Requires-Dist: websockets>=14.2.0
Requires-Dist: loro>=1.5.0 ; python_full_version >= '3.11' and python_full_version < '3.14'
Requires-Dist: typing-extensions>=4.4.0 ; python_full_version < '3.11'
Requires-Dist: docutils>=0.16.0
Requires-Dist: psutil>=5.0
Requires-Dist: itsdangerous>=2.0.0
Requires-Dist: narwhals>=2.0.0
Requires-Dist: packaging
Requires-Dist: msgspec>=0.20.0
Requires-Dist: python-lsp-server>=1.13.0 ; extra == 'lsp'
Requires-Dist: python-lsp-ruff>=2.0.0 ; extra == 'lsp'
Requires-Dist: mcp>=1.0.0 ; extra == 'mcp'
Requires-Dist: pydantic>2 ; extra == 'mcp'
Requires-Dist: marimo[sql] ; extra == 'recommended'
Requires-Dist: marimo[sandbox] ; extra == 'recommended'
Requires-Dist: altair>=5.4.0 ; extra == 'recommended'
Requires-Dist: pydantic-ai-slim[openai]>=1.39.0 ; extra == 'recommended'
Requires-Dist: ruff ; extra == 'recommended'
Requires-Dist: nbformat>=5.7.0 ; extra == 'recommended'
Requires-Dist: pyzmq>=27.1.0 ; extra == 'sandbox'
Requires-Dist: uv>=0.9.21 ; extra == 'sandbox'
Requires-Dist: duckdb>=1.0.0 ; extra == 'sql'
Requires-Dist: polars[pyarrow]>=1.9.0 ; extra == 'sql'
Requires-Dist: sqlglot[rs]>=26.2.0 ; extra == 'sql'
Requires-Python: >=3.10
Project-URL: homepage, https://github.com/marimo-team/marimo
Provides-Extra: lsp
Provides-Extra: mcp
Provides-Extra: recommended
Provides-Extra: sandbox
Provides-Extra: sql
